torchnyan/__init__.py
torchnyan/assertion.py
torchnyan/strategy.py
torchnyan-0.1.3.dist-info/METADATA
torchnyan-0.1.3.dist-info/WHEEL
torchnyan-0.1.3.dist-info/top_level.txt
torchnyan-0.1.3.dist-info/RECORD
